compteur_vues_app/__init__.py
compteur_vues_app/admin.py
compteur_vues_app/apps.py
compteur_vues_app/tests.py
compteur_vues_app/urls.py
compteur_vues_app/utils.py
compteur_vues_app/migrations/0001_initial.py
compteur_vues_app/migrations/0002_article_rename_compteur_vue_vues_and_more.py
compteur_vues_app/migrations/__init__.py
compteur_vues_app/models/__init__.py
compteur_vues_app/models/models.py
compteur_vues_app/views/__init__.py
compteur_vues_app/views/views.py
compteur_vues_app-0.1.dist-info/METADATA
compteur_vues_app-0.1.dist-info/WHEEL
compteur_vues_app-0.1.dist-info/top_level.txt
compteur_vues_app-0.1.dist-info/RECORD
